Metadata-Version: 2.1
Name: proxy-scraper
Version: 1.8
Summary: Get any type of proxies in 1 click!
Home-page: https://github.com/zeloww/proxy_scraper
License: GPLv3+
Keywords: python,py,proxy,proxies,getproxy,getproxies,proxy-scraper,proxies-scraper,scraper
Platform: UNKNOWN
License-File: LICENSE
